Workbook
Name TYPE: Criteria!$A$9:$A$18

Sheet CONTACTS BILLING
A1: KEY CONTACTS
A2: POSITION / ROLL | B2: NAME | C2: COMPANY | D2: MOBILE | E2: EMAIL
A3: Sponsor & Festival Lead | B3: Tyler Hutchinson | C3: Tourism WA
A4: Venue & event promoter | B4: Greg Sleigh Gemma Felton Wendy Quinn Bec Coxall | C4: Optus Stadium
A5: Coordination & programming | B5: Frank Miranda | C5: Perth Italian Festival
A6: Consultation & community engagement | B6: Sal Vallelonga | C6: Sal Vallelonga
A7: Event facilitation & project working group | B7: Jo Metcalf Carol Hodgen | C7: CITS
A8: CaLD participation & engagement | B8: Kate Rowlands | C8: Office of Multicultural Interests
A9: Festival operations & logistics | B9: Kyle Bailey | C9: Kyron Events
A11: Power / Electricians | B11: Sheldon Lobel | C11: Lobel
C12: #VALUE!
B13: BILLING DETAILS
B14: Name:
B15: Company:
B16: Postal:
B17: Address:
B18: ABN:

Sheet CHECKLIST
A1: OPERATIONS / LOGISTICS / INFRASTRUCTURE CHECKLIST
A2: ITEM (EXPENSES) | B2: DETAILS | C2: SUPPLIER | D2: RESPONSIBLE | E2: RFQ SENT | F2: BOOKED | G2: PAID
A3: PORTABLES (BUILDINGS)
A4: 20ft Site Office | B4: KYRON OFFICE | C4: KYRON | E4: FALSE
A5: 20ft Bar container | B5: (TBC) | C5: CR | E5: FALSE
A6: Ticket box (20ft) | B6: (TBC) | C6: CR | E6: FALSE
E7: FALSE
E8: FALSE
E9: FALSE
A10: TOILETS
A11: Portaloos (see toilet calculator) | B11: 30x Portaloos | C11: PERTH HIRE SHOP | E11: FALSE
A12: BOH Portaloos | B12: 2x | C12: PERTH HIRE SHOP | E12: FALSE
A13: ADA Portaloos | B13: 2x | C13: PERTH HIRE SHOP | E13: FALSE
E14: FALSE
E15: FALSE
E16: FALSE
A17: OPERATIONS & LOGISTICS
A18: Event Application | B18: REQUIRED? | C18: KYRON | E18: FALSE
A19: Transport Schedule | B19: TO DO | C19: KYRON | E19: FALSE
A20: Furniture Distro | C20: KYRON | E20: FALSE
A21: Production Schedule | B21: TO DO | C21: KYRON | E21: FALSE
A22: Build Schedule | B22: TO DO | C22: KYRON | E22: FALSE
A23: Event Management Plan | B23: TO DO | C23: KYRON | E23: FALSE
A24: Risk Management Plan | B24: TO DO | C24: KYRON | E24: FALSE
A25: Key Contacts List | B25: TO DO | C25: KYRON | E25: FALSE
A26: Site Map | B26: REV 2 - Draft completed | C26: KYRON | E26: FALSE
A27: Liquor Licence | B27: VL & MIZZICA | C27: KYRON | E27: FALSE
A28: Electrical Form 5 | B28: Electricians to provide | C28: KYRON | E28: FALSE
A29: Major Structures List / Engineering Sign-off | B29: Stage, Marquees, structures, WA Structural, Engineering Specs, Insurances | C29: KYRON | E29: FALSE | AC29: **WORKING ITEMS
A30: FENCING | AC30: ITEM | AD30: QUANTITY | AE30: NOTES
A31: 1.8m Fence | B31: 250m | C31: PERTH HIRE | E31: FALSE | AC31: PICNIC TABLES | AD31: 40
A32: White Picket Fence | B32: 300m | E32: FALSE | AC32: ROUND CAFÉ TABLES | AD32: 30
A33: CCB | B33: 200m | E33: FALSE | AC33: CAFÉ CHAIRS | AD33: =20*5 -> 100
A34: Bollard & Rope | B34: 30m (stage front & large ball) | E34: FALSE | AC34: 3m x 3m Marquee | AD34: 20
A35: Punter Barrier | B35: N/A | E35: FALSE | AC35: Wine Barrels | AD35: 20
A36: Scrim (Branded) | B36: 200m | E36: FALSE | AC36: Bunting | AD36: 300m
A37: STRUCTURES | AC37: Terratrak | AD37: 30pcs
A38: Marquee (3m x 3m) | B38: 20x Red, green and white (Carlisle) | C38: CARLISLE / SWAN EVENTS | E38: FALSE | AC38: Truss Arch (6m) | AD38: 4
A39: Marquees (6m x 3m) | B39: Gable facing out (MERCH tents) | E39: FALSE | AC39: Truss Arch (4m) | AD39: 2
A40: Scaffold centre structure | B40: Seek quotes (Stageset / Ezy Access) | E40: FALSE | AC40: Ballast | AD40: 2 Pallets
A41: Stage | B41: 9m x 7m Trailer Stage | C41: Up Down Events | E41: FALSE | AC41: White Picket Fence | AD41: 300m
E42: FALSE | AC42: 1.8m Fence | AD42: 250m
E43: FALSE | AC43: CCB | AD43: 200m
A44: SITE & TURF MITIGATION | AC44: Popcorn Machine | AD44: 1
A45: Site Manager | B45: See Crew Schedule | E45: FALSE | AC45: Awnings (5m) | AD45: 2
A46: Site Crew | B46: See Crew Schedule | E46: FALSE | AC46: Awnings (4m) | AD46: 3
A47: Trakmatt | B47: 50pcs | C47: PERTH HIRE SHOP | E47: FALSE | AC47: Trailer Stage (9m x 7m) | AD47: 1
A48: Terratrak | B48: 40sqm | C48: EVENT FLOORING WA | E48: FALSE | AC48: Generator (60KVA) | AD48: 2
A49: Ballast | B49: 2 Pallets blocks. + 12x 500kg concrete blocks | E49: FALSE | AC49: Generator (80KVA) | AD49: 1
E50: FALSE | AC50: Generator (7KVA) | AD50: 6
A51: PRODUCTION & AV | AC51: Generator (150KVA) * Stage | AD51: 1
A52: Production Manager | B52: 4 Days | E52: FALSE | AC52: Festoon
A53: Audio | C53: LUX Events / EAVP | E53: FALSE | AC53: Lighting Tower | AD53: 2
A54: Video | C54: LUX Events / EAVP | E54: FALSE | AC54: VMS Board | AD54: 1
A55: Lighting | C55: LUX Events / EAVP | E55: FALSE | AC55: Greenery décor | AD55: 12
A56: Production Labour | C56: LUX Events / EAVP | E56: FALSE | AC56: Site Office (20ft) | AD56: 1
A57: Truss | B57: 4x 6m(W) x 3m (H) Truss Arch 2x 4m (W) x 3m (H) Truss Arch | C57: LUX Events / EAVP | E57: FALSE | AC57: Ticket box (20ft) | AD57: 1
A58: POWER
A59: 60kva | B59: 2 | C59: PERTH HIRE SHOP | E59: FALSE
A60: 80kva | B60: 2 | C60: PERTH HIRE SHOP | E60: FALSE
A61: 55kva | B61: 1 | C61: PERTH HIRE SHOP | E61: FALSE
A62: 23kva | B62: 1 | C62: PERTH HIRE SHOP | E62: FALSE
A63: 7kva | B63: 4 | C63: PERTH HIRE SHOP | E63: FALSE
E64: FALSE
A66: WASTE | AC66: Container Bar (20ft) | AD66: 1
A67: Sulos (FOH) | B67: Create Waste Management Plan to give to VL | C67: Venue to provide (Quay Clean) | E67: FALSE | AC67: Portaloos | AD67: 30
A68: Cleaners | E68: FALSE | AC68: ADA Portaloos | AD68: 2
A69: CoC | E69: FALSE | AC69: Coolroom | AD69: 1
A70: 660L Sulos BOH | E70: FALSE | AC70: Scaffold Tower | AD70: 1 | AE70: Pumptruck & clean required after each night
E71: FALSE | AC71: 1.8m Trestles | AD71: 24
E72: FALSE | AC72: 2.4m Trestles | AD72: 20
A73: SITE FURNITURE | AC73: White Pippee chairs | AD73: 40
A74: 1.8m Trestles | E74: FALSE | AC74: Checkered tablecoth | AD74: 150
A75: 2.4m Trestles | E75: FALSE | AC75: Fire Extinguishers | AD75: 8
A76: Pippee Chairs | E76: FALSE | AC76: Hard Stand Forklift | AD76: 1
A77: Picnic Tables | E77: FALSE | AC77: Telehandler 2.5t Grass Terrain | AD77: 1
A78: Round coffee tables | E78: FALSE | AC78: 10d Scissor | AD78: 1
A79: Café Chairs | E79: FALSE | AC79: Trakmatt | AD79: 50pcs
A80: THEMING / DÉCOR
A81: Plants & Greenery | E81: FALSE
A82: Awnings | E82: FALSE
A83: Wine Barrels | E83: FALSE
A84: Bunting | E84: FALSE
A85: Checkered Tablecloths | B85: 150x | E85: FALSE
E86: FALSE
A87: SAFETY
A88: SWMS / INSURANCES | E88: FALSE
A89: SAFETY OFFICER | B89: 9 Days | E89: FALSE
A90: JSA | E90: FALSE
A91: Safety Signage, Bunting Kit | E91: FALSE
A92: EMERGENCY EVAC KIT | E92: FALSE
A93: Fire Extinguishers | C93: HECS Fire & Safety | E93: FALSE
A94: MACHINERY
A95: 2.5t ALL TERRAIN FORKLIFT | C95: PERTH HIRE SHOP | E95: FALSE
A96: 10D SCISSOR | C96: PERTH HIRE SHOP | E96: FALSE
A97: TRAY BACK UTE | B97: KYRON | E97: FALSE
E98: FALSE
E99: FALSE
E100: FALSE
A101: POWER
...

Sheet POWER
A1: POWER REQUIREMENTS
A2: GENERATORS
A3: KVA | B3: QTY | C3: NOTES /LOCATION | D3: DELIVERY | E3: COLLECTION
A4: 150 | C4: STAGE | D4: 46237 | E4: 46246
A5: 60kva | B5: 2 | C5: S60 | D5: 46265 | E5: 46246
A6: 80kva | B6: 2 | C6: OPS COMPOUND | D6: 46237 | E6: 46246
A7: 55kva | B7: 1 | C7: VENDORS | D7: 46237 | E7: 46246
A8: 23kva | B8: 1 | C8: / | D8: 46237 | E8: 46246
A9: 7kva | B9: 4 | C9: ACTIVITIES / SPARES | D9: 46237 | E9: 46246
A11: POWER DISTRO / CABLE COVER
A12: OUTLETS | B12: QTY REQUIRED | C12: NOTES /LOCATION | D12: DELIVERY | E12: COLLECTION
A13: 63a | B13: 1 | C13: STAGE | D13: 46237 | E13: 46246
A14: 32a | B14: 8 | C14: Vendors BOH
A15: 15a | B15: 1 | C15: OPS COMPOUND | D15: 46236 | E15: 46246
A16: 10a | B16: 2 | C16: VENDORS | D16: 46236 | E16: 46246
B17: 1 | C17: BRIDGE | D17: 46237 | E17: 46246
B18: 4 | C18: ACTIVITIES / SPARES | D18: 46237 | E18: 46246
B19: 50 | C19: CABLETRAP
A20: SITE LX
A21: ITEM | B21: QTY | C21: NOTES /LOCATION | D21: DELIVERY | E21: COLLECTION
B22: 1 | C22: STAGE | D22: 46237 | E22: 46246
A23: Fluros | B23: 20 | C23: Marquee lighting
B24: 1 | C24: OPS COMPOUND | D24: 46236 | E24: 46246
B25: 2 | C25: VENDORS | D25: 46236 | E25: 46246
B26: 1 | C26: BRIDGE | D26: 46237 | E26: 46246
B27: 4 | C27: ACTIVITIES / SPARES | D27: 46237 | E27: 46246
A29: ELECTRICIANS / PERMITS
A30: ITEM | B30: QTY | C30: NOTES /LOCATION | D30: DELIVERY | E30: COLLECTION
B31: 1 | C31: STAGE | D31: 46237 | E31: 46246
A32: 100 | B32: 0 | C32: n/a
A33: 80 | B33: 1 | C33: OPS COMPOUND | D33: 46236 | E33: 46246
A34: 60 | B34: 2 | C34: VENDORS | D34: 46236 | E34: 46246
A35: 20 | B35: 1 | C35: BRIDGE | D35: 46237 | E35: 46246
A36: 7 | B36: 4 | C36: ACTIVITIES / SPARES | D36: 46237 | E36: 46246

Sheet ESTIMATE
A1: Infrastructure | C1: Estimate | E1: QUOTE | F1: TOTAL | G1: NOTES | J1: OPERATIONS / LOGISTICS | K1: SITE MANAGEMENT / CREW | L1: KYRON
A2: Marquees / Structures/ Furniture | C2: 35000 | E2: 25000 | J2: MGMT DELIVERY | K2: ONSITE DELIVERY | L2: TOTAL
A3: Portaloos | C3: 8000 | E3: 10906 | F3: =BUDGET!D28 -> 10906 | I3: 1 | J3: =SUM(D14:D17) -> 51620 | K3: =C21+C20+C19+C18 -> 11112 | L3: =SUM(J3+K3) -> 62732
A4: LX / Festoon | C4: 10000 | E4: 10000
A5: Portables (Site Office, Ticket Box) | C5: 5000 | E5: 5000 | F5: 2000 | I5: 2 | J5: =SUM(E14:E17) -> 40500 | K5: 24085 | L5: =J5+K5 -> 64585
A6: Fencing (White Picket, CCB) | C6: 12000 | E6: 8000 | F6: =BUDGET!D50 -> 7707.5 | L6: =L5*0.1 -> 6458.5 | M6: GST
A7: Machinery / Fuel | C7: 8000 | E7: 3300 | F7: =BUDGET!D57 -> 3000 | L7: =L5+L6 -> 71043.5
A8: Generators / Power Distro | C8: 35000 | E8: 25000
A9: Theming / Décor / Signage | C9: 35000 | E9: 10000
A10: Cool Rooms / Site Misc | C10: 1000 | E10: 4000
A11: Turf Mitigation | C11: 2000 | E11: 2000
C12: =SUM(C2:C11) -> 151000 | D12: =#REF!+#REF! -> #REF! | E12: =SUM(E2:E11) -> 103206 | F12: =C12-E12 -> 47794
A13: Operations / Logistics (inc Staffing) | C13: HOURS | E13: POSSIBLE REDUCE
A14: Project Manager | C14: 32500 | D14: 32500 | E14: 32500 | F14: See MGMT Schedule
A15: Operations Manager | C15: 8000 | D15: 5000 | E15: 8000 | F15: See MGMT Schedule
A16: Admin/Account Manager | D16: 6520 | E16: 0 | F16: See MGMT Schedule
A17: Safety Officer (Onsite) | D17: =8*950 -> 7600 | E17: 0 | F17: Venue to provide
A18: Site Manager | D18: ='CREW SCHEDULE'!J10 -> 11420.5 | E18: 0 | F18: See MGMT Schedule
A19: Forklift Operater | C19: ='CREW SCHEDULE'!L3 -> 3249.5 | D19: ='CREW SCHEDULE'!M3 -> 1909.5 | E19: 3249 | F19: See Site Crew Schedule
A20: EWP Operater | C20: ='CREW SCHEDULE'!M3 -> 1909.5 | D20: ='CREW SCHEDULE'!L3 -> 3249.5 | E20: 1909 | F20: See Site Crew Schedule
A21: Site Crew | C21: ='CREW SCHEDULE'!K3 -> 5953 | D21: 8340 | E21: 7000 | F21: See Site Crew Schedule
C22: =SUM(C14:C21) -> 51612 | D22: =SUM(#REF!) -> #REF! | E22: =SUM(E14:E21) -> 52658
A23: Staging / AV | C23: Estimate $
A24: Stage (9m x 7m) | C24: 15000 | E24: 15000
A25: Backline | C25: 2500 | E25: 2000
A26: AV | C26: 25000 | E26: 10000 | F26: 10000
A27: Production Manager / Stage Manager | C27: 5000 | E27: 5000
A28: Stage Manager | C28: 5 | E28: 0
A29: AV Labour | C29: 3000 | E29: 2000
A30: Truss Arches | C30: 5000 | E30: 5000
C31: =SUM(C24:C30) -> 55505 | D31: =#REF!+#REF! -> #REF! | E31: =SUM(E24:E30) -> 39000
A32: Programming / Performers | C32: $
A33: Roving Performers | C33: 15000 | E33: 7500
A34: Stage/ DJ Performers | C34: 40000 | E34: 20000
A35: Face painters/ artists | C35: 3500
A36: Fireworks | C36: 30000 | E36: 10000
A37: Programming | C37: 10000 | D37: =SUM(C33:C36) -> 88500 | E37: 0
A38: Subtotal | C38: =SUM(C33:C37) -> 98500 | D38: =D36+D37 -> 88500 | E38: =SUM(E33:E37) -> 37500
A39: TOTAL | C39: =C38+C31+C22+C12 -> 356617 | E39: =E38+E31+E22+E12 -> 232364
B40: GST | C40: =C39*0.1 -> 35661.7
B41: TOTAL | C41: =C39+C40 -> 392278.7 | E41: =E39*1.1 -> 255600.4

Sheet CREW SCHEDULE
A1: CREW SCHEDULE | J1: $ / ROLE | ACTUALS
A2: Saturday 01/08/26 | E2: ROLE | F2: $ / HR | RATE | G2: TOTAL ($) | J2: SITE MANAGER ($) | K2: SITE CREW ($) | L2: FORK OPS ($) | M2: EWP OPS ($)
A3: START | B3: FINISH | C3: SCHEDULED HRS (Inc BREAKS) | D3: ACTUALS | I3: ONSITE | J3: =G4+G12+G28+G36+G46+G59+G51+G68+G73+G81 -> 10180.5 | K3: {=G5:G6+G13+G21:G22+G29:G30+G37:G39+G52:G53+G54:G55+G61:G62+G69+G74:G75+G82:G83} -> 5953 | L3: =G24+G39+G53+G77+G84 -> 3249.5 | M3: =G31+G76+G23 -> 1909.5
A4: 8:00AM | B4: 4:00PM | C4: 5 | D4: 7.5 | E4: SITE MANAGER | F4: 125 | G4: =D4*F4 -> 937.5 | I4: PRE / POST | J4: 1240 | K4: 5652.5
A5: 8:00AM | B5: 4:00PM | C5: 5 | D5: 7.5 | E5: SITE CREW 1 | F5: 69 | G5: =D5*F5 -> 517.5 | K5: #N/A
A6: 8:00AM | B6: 1:00p, | C6: 5 | D6: 7.5 | E6: SITE CREW 2 | F6: 69 | G6: =D6*F6 -> 517.5
D7: 7.5
F9: DAILY TOTAL ($) | G9: =SUM(G4:G7) -> 1972.5
A10: Sunday 02/08/2026 | C10: BUMP-IN | D10: BUMP-IN | J10: =J3+J4 -> 11420.5
A11: START | B11: FINISH | C11: TOTAL HRS (Inc BREAKS) | D11: TOTAL HRS (Inc BREAKS)
F12: 125 | G12: =D12*F12 -> 0
F13: 82 | G13: =D13*F13 -> 0
F17: DAILY TOTAL ($) | G17: =SUM(G12:G16) -> 0
A18: Monday 03/08/2026 | C18: BUMP-IN | D18: BUMP-IN
A19: START | B19: FINISH | C19: TOTAL HRS (Inc BREAKS) | D19: TOTAL HRS (Inc BREAKS)
A20: 7:00AM | B20: 7:00PM | C20: 11.5 | D20: 11.5 | E20: SITE MANAGER | F20: 100 | G20: =D20*F20 -> 1150
A21: 7:00AM | B21: 6:00PM | C21: 10.5 | D21: 10.5 | E21: SITE CREW 1 | F21: 56 | G21: =D21*F21 -> 588
A22: 7:00AM | B22: 5:00PM | C22: 9.5 | D22: 9.5 | E22: SITE CREW 2 | F22: 56 | G22: =D22*F22 -> 532
A23: 7:00AM | B23: 5:00PM | C23: 9.5 | D23: 9.5 | E23: EWP OP | F23: 67 | G23: =D23*F23 -> 636.5 | L23: =G24+G32+G37+G52+G77+G84 -> 3778
A24: 7:00AM | B24: 5:00PM | C24: 9.5 | D24: 9.5 | E24: FORK OP | F24: 67 | G24: =D24*F24 -> 636.5
F25: DAILY TOTAL ($) | G25: =SUM(G20:G24) -> 3543
A26: Tuesday 04/08/2026 | C26: BUMP-IN | D26: BUMP-IN
A27: START | B27: FINISH | C27: TOTAL HRS (Inc BREAKS) | D27: TOTAL HRS (Inc BREAKS)
A28: 7:00AM | B28: 7:00PM | C28: 11.5 | D28: 11.5 | E28: SITE MANAGER | F28: 100 | G28: =D28*F28 -> 1150
A29: 7:00AM | B29: 6:00PM | C29: 10.5 | D29: 10.5 | E29: SITE CREW 1 | F29: 56 | G29: =D29*F29 -> 588
A30: 7:00AM | B30: 5:00PM | C30: 9.5 | D30: 9.5 | E30: SITE CREW 2 | F30: 56 | G30: =D30*F30 -> 532
A31: 7:00AM | B31: 5:00PM | C31: 9.5 | D31: 9.5 | E31: EWP OP | F31: 67 | G31: =D31*F31 -> 636.5
A32: 7:00AM | B32: 5:00PM | C32: 9.5 | D32: 9.5 | E32: FORK OP | F32: 67 | G32: =D32*F32 -> 636.5
F33: DAILY TOTAL ($) | G33: =SUM(G28:G32) -> 3543
A34: Wednesday 05/08/2026 | C34: AC MILAN VS INTER | D34: AC MILAN VS INTER
A35: START | B35: FINISH | C35: TOTAL HRS (Inc BREAKS) | D35: TOTAL HRS (Inc BREAKS)
A36: 7:00AM | B36: 9:30PM | C36: 13.5 | D36: 13.5 | E36: SITE MANAGER | F36: 100 | G36: =D36*F36 -> 1350
A37: 7:00AM | B37: 7:00PM | C37: 11.5 | D37: 11.5 | E37: SITE CREW 1 | F37: 56 | G37: =D37*F37 -> 644
A38: 7:00AM | B38: 6:00PM | C38: 10.5 | D38: 10.5 | E38: SITE CREW 2 | F38: 56 | G38: =D38*F38 -> 588
A39: 7:00AM | B39: 6:00PM | C39: 10.5 | D39: 10.5 | E39: FORKS | F39: 67 | G39: =D39*F39 -> 703.5
D40: 10.5
A41: 5:30PM | B41: 9:30PM | C41: 4 | D41: 4 | E41: SITE OPS | F41: 69 | G41: =D41*F41 -> 276
A42: 5:30PM | B42: 9:30PM | C42: 4 | D42: 4 | E42: SITE OPS | F42: 69 | G42: =D42*F42 -> 276
F43: DAILY TOTAL ($) | G43: =SUM(G36:G42) -> 3837.5
A44: Thursday 06/08/2026 | C44: DOWN DAY | D44: DOWN DAY
A45: START | B45: FINISH | C45: TOTAL HRS (Inc BREAKS) | D45: TOTAL HRS (Inc BREAKS)
A46: 9:00am | B46: 3:00pm | C46: 5.5 | D46: 5.5 | E46: SITE MANAGER | F46: 101 | G46: =D46*F46 -> 555.5
F48: DAILY TOTAL ($) | G48: =SUM(G46) -> 555.5
A49: Friday 07/08/2026 | C49: Open Training Inter & Juventus | D49: Open Training Inter & Juventus
A50: START | B50: FINISH | C50: TOTAL HRS (Inc BREAKS) | D50: TOTAL HRS (Inc BREAKS)
A51: 7:00AM | B51: 9:30PM | C51: 13.5 | D51: 13.5 | E51: SITE MANAGER | F51: 100 | G51: =D51*F51 -> 1350
A52: 7:00AM | B52: 7:00PM | C52: 10.5 | D52: 10.5 | E52: SITE CREW 1 | F52: 56 | G52: =D52*F52 -> 588
A53: 7:00AM | B53: 6:00PM | C53: 9.5 | D53: 9.5 | E53: FORKS | F53: 67 | G53: =D53*F53 -> 636.5
A54: 5:30PM | B54: 9:30PM | C54: 4 | D54: 4 | E54: SITE CREW | F54: 69 | G54: =D54*F54 -> 276
A55: 5:30PM | B55: 9:30PM | C55: 4 | D55: 4 | E55: SITE CREW | F55: 69 | G55: =D55*F55 -> 276
F56: DAILY TOTAL ($) | G56: =SUM(G51:G55) -> 3126.5
A57: Saturday 08/08/2026 | C57: INTER VS JUVENTUS | D57: INTER VS JUVENTUS
A58: START | B58: FINISH | C58: TOTAL HRS (Inc BREAKS) | D58: TOTAL HRS (Inc BREAKS)
A59: 6:00AM | B59: 5:30PM | C59: 11 | D59: 11 | E59: SITE MANAGER | F59: 100 | G59: =D59*F59 -> 1100
A60: 5:30PM | B60: 12:00am | C60: 6 | D60: 6 | E60: SITE / OPS MANAGER | F60: 125 | G60: =D60*F60 -> 750
A61: 7:00AM | B61: 7:00PM | C61: 10.5 | D61: 10.5 | E61: SITE CREW 1 | F61: 69 | G61: =D61*F61 -> 724.5
A62: 7:00AM | B62: 6:00PM | C62: 9.5 | D62: 9.5 | E62: SITE CREW 2 | F62: 69 | G62: =D62*F62 -> 655.5
D63: 9.5 | G63: =D63*F63 -> 0
F64: DAILY TOTAL ($) | G64: =SUM(G59:G63) -> 3230
A66: Sunday 09/08/2026 | C66: AFL FOOTBALL GAME (TBC) | D66: AFL FOOTBALL GAME (TBC)
A67: START | B67: FINISH | C67: TOTAL HRS (Inc BREAKS) | D67: TOTAL HRS (Inc BREAKS)
A68: 7:00AM | B68: 7:00PM | C68: 11.5 | D68: 11.5 | E68: SITE MANAGER | F68: 125 | G68: =D68*F68 -> 1437.5
A69: 7:00AM | B69: 7:00PM | C69: 11.5 | D69: 11.5 | E69: SITE CREW 1 | F69: 74 | G69: =D69*F69 -> 851
F70: DAILY TOTAL ($) | G70: =SUM(G68:G69) -> 2288.5
A71: Monday 10/08/2026 | C71: BUMP-OUT | D71: BUMP-OUT
A72: START | B72: FINISH | C72: TOTAL HRS (Inc BREAKS) | D72: TOTAL HRS (Inc BREAKS)
A73: 7:00AM | B73: 7:00PM | C73: 11.5 | D73: 11.5 | E73: SITE MANAGER | F73: 100 | G73: =D73*F73 -> 1150
A74: 7:00AM | B74: 6:00PM | C74: 10.5 | D74: 10.5 | E74: SITE CREW 1 | F74: 56 | G74: =D74*F74 -> 588
A75: 7:00AM | B75: 5:00PM | C75: 9.5 | D75: 9.5 | E75: SITE CREW 2 | F75: 56 | G75: =D75*F75 -> 532
A76: 7:00AM | B76: 5:00PM | C76: 9.5 | D76: 9.5 | E76: EWP OP | F76: 67 | G76: =D76*F76 -> 636.5
A77: 7:00AM | B77: 5:00PM | C77: 9.5 | D77: 9.5 | E77: FORK OP | F77: 67 | G77: =D77*F77 -> 636.5
F78: DAILY TOTAL ($) | G78: =SUM(G73:G77) -> 3543
A79: Tuesday 11/08/2026 | C79: BUMP-OUT | D79: BUMP-OUT
A80: START | B80: FINISH | C80: TOTAL HRS (Inc BREAKS) | D80: TOTAL HRS (Inc BREAKS)
A81: 7:00AM | B81: 7:00PM | C81: 11.5 | D81: 11.5 | E81: SITE MANAGER | F81: 100 | G81: =D81*F81 -> 1150
A82: 7:00AM | B82: 6:00PM | C82: 10.5 | D82: 10.5 | E82: SITE CREW 1 | F82: 56 | G82: =D82*F82 -> 588
A83: 7:00AM | B83: 5:00PM | C83: 9.5 | D83: 9.5 | E83: SITE CREW 2 | F83: 56 | G83: =D83*F83 -> 532
A84: 7:00AM | B84: 5:00PM | C84: 9.5 | D84: 9.5 | E84: FORK OP | F84: 67 | G84: =D84*F84 -> 636.5
F85: DAILY TOTAL ($) | G85: =SUM(G81:G84) -> 2906.5
F86: TOTAL | G86: =G85+G78+G70+G64+G56+G48+G43+G33+G25+G17+G9 -> 28546
F87: GST | G87: =G86*0.1 -> 2854.6
F88: TOTAL (inc GST) | G88: =SUM(G86:G87) -> 31400.6

Sheet MGMT SCHEDULE
A1: OPERATIONS / LOGISTICS MGMT
A2: 1/6/2026 | WEEK 1 | C2: TASKS | D2: HRS | E2: COMPLETED | F2: ROLE | G2: $ / HR | RATE | H2: TOTAL ($)
C3: Weekly Team Meetings | D3: 3 | E3: FALSE
B4: 1 | C4: Site Map Development | D4: 10 | E4: FALSE | F4: Project Manager | G4: 115
B5: 2 | C5: Master Schedule | D5: 3 | E5: FALSE
B6: 3 | C6: Scope Requirements | D6: 3 | E6: FALSE
B7: 4 | C7: RFQ Suppliers | D7: 3 | E7: FALSE
B8: 5 | C8: Risk Management Plan 001 | D8: 4 | E8: FALSE
B9: 6 | C9: Insurance PPL / Vendor Insurances | D9: 3 | E9: FALSE
C10: TOTAL HRS (ESTIMATE) | D10: =SUM(D3:D9) -> 29 | H10: =G4*D10 -> 3335
A11: 8/6/2026 | WEEK 2 | C11: TASKS | D11: HRS | E11: COMPLETED | F11: ROLE | G11: $ / HR | RATE | H11: TOTAL ($)
C12: Weekly Team Meetings | D12: 3 | E12: FALSE
B13: 1 | C13: Site Map Revisions | D13: 3 | E13: FALSE | F13: Project Manager | G13: 115
B14: 2 | C14: Major Structures | D14: 4 | E14: FALSE | F14: Project Manager
B15: 3 | C15: RFQ Suppliers / Insurances | D15: 3 | E15: FALSE | F15: Operations Manager
B16: 4 | C16: Budget | D16: 3 | E16: FALSE | F16: Admin/Accounts
B17: 5 | C17: Risk Management Plan 002 | D17: 6 | E17: FALSE | F17: Project Manager
B18: 6 | C18: EMP 001 | D18: 4 | E18: FALSE | F18: Project Manager
C19: TOTAL HRS (ESTIMATE) | D19: =SUM(D12:D18) -> 26 | H19: =G13*D19 -> 2990
A20: 15/6/2026 | WEEK 3 | C20: TASKS | D20: HRS | E20: COMPLETED | F20: ROLE | G20: $ / HR | RATE | H20: TOTAL ($)
C21: Weekly Team Meetings | D21: 3 | E21: FALSE
B22: 1 | C22: Site Map (Revs) | D22: 1 | E22: FALSE | F22: Project Manager | G22: 115
B23: 2 | C23: Master Schedule Updates | D23: 3 | E23: FALSE
B24: 3 | C24: Transport Schedule | D24: 3 | E24: FALSE
B25: 4 | C25: Book Infrastructure Suppliers | D25: 3 | E25: FALSE
B26: 5 | C26: Risk Management Plan 003 | For Review | D26: 3 | E26: TRUE
B27: 6 | C27: Staging / AV Suppliers | D27: 3 | E27: FALSE
C28: TOTAL HRS (ESTIMATE) | D28: 22 | H28: =G22*D28 -> 2530
A29: 22/6/2026 | WEEK 4 | C29: TASKS | D29: HRS | E29: COMPLETED | F29: ROLE | G29: $ / HR | RATE | H29: TOTAL ($)
C30: Weekly Team Meetings | D30: 3 | E30: FALSE
B31: 1 | C31: Site Map Development | D31: 3 | E31: FALSE | F31: Project Manager | G31: 115
B32: 2 | C32: Master Schedule | D32: 3 | E32: FALSE
B33: 3 | C33: Scope Requirements | D33: 3 | E33: FALSE
B34: 4 | C34: Security / Asset Protection | D34: 3 | E34: FALSE
B35: 5 | C35: Crew Scheduling / Confirmations | D35: 4 | E35: FALSE
B36: 6 | C36: Budget / Review / Final Sign-off | D36: 3 | E36: FALSE
C37: TOTAL HRS (ESTIMATE) | D37: 22 | H37: =G31*D37 -> 2530
A38: 29/6/2026 | WEEK 5 | C38: TASKS | D38: HRS | E38: COMPLETED | F38: ROLE | G38: $ / HR | RATE | H38: TOTAL ($)
C39: Weekly Team Meetings | D39: 3 | E39: FALSE
B40: 1 | C40: Site Map Development | D40: 2 | E40: FALSE | F40: Project Manager | G40: 115
B41: 2 | C41: Master Schedule Confirmation / Sign-off | D41: 4 | E41: FALSE | F41: Project Manager | G41: 115
B42: 3 | C42: Transport / Logistics Schedule | D42: 3 | E42: FALSE | F42: Ops Manager
B43: 4 | C43: Confirm Suppliers / Budget Sign-off | D43: 4 | E43: FALSE
B44: 5 | C44: Staffing Schedule confirmed | D44: 4 | E44: FALSE
B45: 6 | D45: 4 | E45: FALSE
B46: 7 | C46: General Misc / SWMS docs | D46: 3 | E46: FALSE
C47: TOTAL HRS (ESTIMATE) | D47: 22 | H47: =G40*D47 -> 2530
A48: 05/7/2026 | WEEK 1 | C48: TASKS | D48: HRS | E48: COMPLETED | F48: ROLE | G48: $ / HR | RATE | H48: TOTAL ($)
C49: Weekly Team Meetings | D49: 3 | E49: FALSE
B50: 1 | C50: Scheduling Vendors/Contractors | D50: 3 | E50: FALSE | F50: Project Manager | G50: 115
B51: 2 | C51: Master Schedule Updates | D51: 3 | E51: FALSE
B52: 3 | C52: Budget / Review Final | D52: 3 | E52: FALSE | F52: Admin/Accounts (1.5hrs) PM (1.5hrs)
B53: 4 | C53: First Aid / Medical Sign-off | D53: 3 | E53: FALSE
B54: 5 | C54: Waste Management | D54: 4 | E54: FALSE
B55: 6 | C55: General Misc | D55: 3 | E55: FALSE
C56: TOTAL HRS (ESTIMATE) | D56: =SUM(D49:D55) -> 22 | H56: =G50*D56 -> 2530
A57: 12/7/2026 | WEEK 1 | C57: TASKS | D57: HRS | E57: COMPLETED | F57: ROLE | G57: $ / HR | RATE | H57: TOTAL ($)
C58: Weekly Team Meetings | D58: 3 | E58: FALSE
B59: 1 | C59: Scheduling Vendors/Contractors | D59: 3 | E59: FALSE | F59: Project Manager | G59: 115
B60: 2 | C60: Master Schedule Updates | D60: 3 | E60: FALSE
B61: 3 | C61: Budget / Review Final | D61: 3 | E61: FALSE | F61: Admin/Accounts (1.5hrs) PM (1.5hrs)
B62: 4 | C62: First Aid / Medical Sign-off | D62: 3 | E62: FALSE
B63: 5 | C63: Waste Management | D63: 4 | E63: FALSE
B64: 6 | C64: General Misc | D64: 3 | E64: FALSE
C65: TOTAL HRS (ESTIMATE) | D65: =SUM(D58:D64) -> 22 | H65: =G59*D65 -> 2530
A66: 19/7/2026 | WEEK 1 | C66: TASKS | D66: HRS | E66: COMPLETED | F66: ROLE | G66: $ / HR | RATE | H66: TOTAL ($)
C67: Weekly Team Meetings | D67: 3 | E67: FALSE
B68: 1 | C68: Scheduling Vendors/Contractors | D68: 3 | E68: FALSE | F68: Project Manager | G68: 115
B69: 2 | C69: Master Schedule Updates | D69: 3 | E69: FALSE
B70: 3 | C70: Budget / Review Final | D70: 3 | E70: FALSE | F70: Admin/Accounts (1.5hrs) PM (1.5hrs)
B71: 4 | C71: First Aid / Medical Sign-off | D71: 3 | E71: FALSE
B72: 5 | C72: Waste Management | D72: 4 | E72: FALSE
B73: 6 | C73: General Misc | D73: 3 | E73: FALSE
C74: TOTAL HRS (ESTIMATE) | D74: =SUM(D67:D73) -> 22 | H74: =G68*D74 -> 2530
A75: 26/7/2026 | WEEK 1 | C75: TASKS | D75: HRS | E75: COMPLETED | F75: ROLE | G75: $ / HR | RATE | H75: TOTAL ($)
C76: Weekly Team Meetings | D76: 3 | E76: FALSE
B77: 1 | C77: Scheduling Vendors/Contractors | D77: 3 | E77: FALSE | F77: Project Manager | G77: 115
B78: 2 | C78: Master Schedule Updates | D78: 3 | E78: FALSE
B79: 3 | C79: Budget / Review Final | D79: 3 | E79: FALSE | F79: Admin/Accounts (1.5hrs) PM (1.5hrs)
B80: 4 | C80: First Aid / Medical Sign-off | D80: 3 | E80: FALSE
B81: 5 | C81: Waste Management | D81: 4 | E81: FALSE
B82: 6 | C82: General Misc | D82: 3 | E82: FALSE
C83: TOTAL HRS (ESTIMATE) | D83: =SUM(D76:D82) -> 22 | H83: =G77*D83 -> 2530
A84: 01/8/2026 | WEEK 1 | C84: TASKS | D84: HRS | E84: COMPLETED | F84: ROLE | G84: $ / HR | RATE | H84: TOTAL ($)
C85: Weekly Team Meetings | D85: 3 | E85: FALSE
B86: 1 | C86: Scheduling Vendors/Contractors | D86: 3 | E86: FALSE | F86: Project Manager | G86: 115
B87: 2 | C87: Master Schedule Updates | D87: 3 | E87: FALSE
B88: 3 | C88: Budget / Review Final | D88: 3 | E88: FALSE | F88: Admin/Accounts (1.5hrs) PM (1.5hrs)
B89: 4 | C89: First Aid / Medical Sign-off | D89: 3 | E89: FALSE
B90: 5 | C90: Waste Management | D90: 4 | E90: FALSE
B91: 6 | C91: General Misc | D91: 3 | E91: FALSE
C92: TOTAL HRS (ESTIMATE) | D92: =SUM(D85:D91) -> 22 | H92: =G86*D92 -> 2530

Sheet BUDGET
A1: EXPENDITURE BUDGET
A3: APPROVER: | G3: RESPONSIBLE: KYRON PTY LTD
A4: ITEM | B4: SUPPLIER | C4: INSURANCE | D4: QUOTED ($) ex gst | E4: ACTUAL ($) inc GST | F4: QUOTE (link) | G4: APPROVED | H4: PAID | I4: NOTES | Y4: RFQ # | Z4: RFQ REGISTER
A5: POWER / ELECTRICIANS
A6: GENERATORS 2x 80kva 2x 60kva 2x 55kva 1x 23kva 4x 7kva) | B6: PERTH HIRE SHOP | D6: =1400+1000+1000+400+1400+2160 -> 7360 | Y6: RFQ-001 | Z6: QUOTE 1 | AA6: TOILETS
A7: Generator Transport | B7: PERTH HIRE SHOP | D7: 2160
A8: POWER DISTRO | B8: LOBEL | Y8: PERTH HIRE SHOP
A9: ELECTRICIANS / LABOUR | B9: LOBEL | Z9: ITEM(S) | AA9: 40x Portaloos
A10: FORM 5 SIGN-OFF | B10: LOBEL | AA10: 2x ADA Portaloos
A11: LX TOWER | B11: PERTH HIRE SHOP | D11: =325*2 -> 650
A12: SITE LX | FESTOON | B12: TBC
A13: TOTAL | D13: =SUM(D6:D12) -> 10170 | E13: =SUM(E6:E12) -> 0 | Z13: DELIVERY | AA13: Delivery
A14: PORTABLES | Z14: COLLECTION | AA14: 46237
A15: 20ft Site Office | B15: KYRON | D15: 350 | Z15: LOCATION | AA15: 46245
A16: 20ft Box Office | AA16: OPTUS STADIUM
A17: 20ft Container Bar | Y17: RFQ-002 | Z17: QUOTE 2
A18: Transport | B18: PHS | Z18: ITEMS | AA18: MACHINERY / TRAKMATT
AA19: PERTH HIRE SHOP
A20: TOTAL | D20: =SUM(D15:D19) -> 350 | E20: =SUM(E15:E19) -> 0 | AA20: 2.5t Hardstand Forklift
A21: TOILETS | AA21: 2.5t Telehandler (Grass terrain tyres)
A22: 30x Portaloos | B22: PERTH HIRE SHOP | D22: =85*30 -> 2550 | F22: QUOTE | AA22: 10D Scissor
A23: 2x ADA Portaloos | B23: PERTH HIRE SHOP | D23: =158*2 -> 316 | Z23: DELIVERY | AA23: Trakmatt (50pcs)
A24: Transport | B24: PERTH HIRE SHOP | D24: =650 -> 650 | Z24: COLLECTION | AA24: 46235
A25: Weekend Callout | B25: PERTH HIRE SHOP | D25: =350 -> 350
A26: Toilet servicing / pump-out (4) | B26: PERTH HIRE SHOP | D26: =1760*4 -> 7040 | Z26: LOCATION | AA26: 46245
AA27: OPTUS STADIUM
A28: TOTAL | D28: =SUM(D22:D27) -> 10906 | E28: =SUM(E22:E27) -> 0 | Y28: RFQ-003 | Z28: QUOTE 3
A29: STAGING / AV | Z29: ITEMS | AA29: FENCING / WHITE PICKET / CCB
A30: Stage (9m x 7m) Trailer Stage | AA30: CBWA
A31: Audio | AA31: 2.5t Hardstand Forklift
A32: Lighting | AA32: 2.5t Telehandler (Grass terrain tyres)
AA33: 10D Scissor
Z34: DELIVERY | AA34: Trakmatt (50pcs)
A35: TOTAL | D35: =SUM(D30:D34) -> 0 | E35: =SUM(E30:E34) -> 0 | Z35: COLLECTION | AA35: 46235
A36: MARQUEES / STRUCTURES | Z36: LOCATION | AA36: 46245
AA37: OPTUS STADIUM
Y38: RFQ-003 | Z38: QUOTE 3
Z39: ITEMS | AA39: MARQUEES
AA40: CBWA
AA41: 18x (3m x 3m) Red/green/white marquees
A42: TOTAL | D42: =SUM(D37:D41) -> 0 | E42: =SUM(E37:E41) -> 0 | AA42: 2x (6m x 3m) Hoeker P-Series Structure
A43: FENCING | AA43: 2x (12m x 3m) Hoeker
A44: 1.8m Fence (INSTALLED) - Inc 3 gates - 2 double 1 single - Inc bracing every 1panel with extra weight for wind rating up to 100km/h - Inc 1x pallet of white blocks (feet) | B44: PERTH HIRE SHOP | D44: =12.35*250 -> 3087.5 | Z44: DELIVERY
A45: CCB | B45: PERTH HIRE SHOP | D45: =60*9 -> 540 | Z45: COLLECTION | AA45: 46235
A46: Transport | B46: PERTH HIRE SHOP | D46: =380 -> 380 | Z46: LOCATION | AA46: 46245
A47: White Picket | B47: CBWA | D47: =(14*250) -> 3500
A48: Transport | B48: CBWA | D48: 200 | AA48: OPTUS STADIUM
A50: TOTAL | D50: =SUM(D44:D49) -> 7707.5 | E50: =SUM(E44:E49) -> 0
A51: MACHINERY
A52: 3t Rough Terrain Forklift (weekly hire) | B52: PERTH HIRE SHOP | D52: =2*700 -> 1400
A53: 8.1m Scissor Lift Rough Terrain 2755RT 4x4 27ft | B53: PERTH HIRE SHOP | D53: =500 -> 500
A54: Transport | B54: PERTH HIRE SHOP | D54: 800
A55: Deisel | 100l @ $3.00/l | B55: KYRON | D55: =3*100 -> 300
A57: TOTAL | D57: =SUM(D52:D56) -> 3000 | E57: =SUM(E52:E56) -> 0
A58: OPERATIONS (inc Staff)
A64: TOTAL | D64: =SUM(D59:D63) -> 0 | E64: =SUM(E59:E63) -> 0
A65: SITE & TURF MITIGATION
A66: Trakmatt (50x) | B66: PERTH HIRE SHOP | D66: =50*18 -> 900
A67: Terratrak | D67: 1200
A71: TOTAL | D71: =SUM(D66:D70) -> 2100 | E71: =SUM(E66:E70) -> 0
A72: FURNITURE (SITE / PATRON)
A78: TOTAL | D78: =SUM(D73:D77) -> 0 | E78: =SUM(E73:E77) -> 0
A79: THEMING / DÉCOR
A85: TOTAL | D85: =SUM(D80:D84) -> 0 | E85: =SUM(E80:E84) -> 0
A86: MISCELANEOUS
A87: VMS Board | C87: PERTH HIRE SHOP | D87: 200
A92: TOTAL | D92: =SUM(D87:D91) -> 200 | E92: =SUM(E87:E91) -> 0
A93: SITE TOTAL | D93: =SUM(D92,D85,D78,D71,D64,D57,D50,D42,D35,D28,D20,D13) -> 34433.5 | E93: =SUM(E92,E85,E78,E71,E64,E57,E50,E42,E35,E28,E20,E13) -> 0

Sheet TOPLINE SCHEDULE
A1: TIME | B1: 1 | C1: 2 | D1: 3 | E1: 4 | F1: 5 | G1: 6 | H1: 7 | I1: 8 | J1: 9 | K1: 10 | L1: 11 | M1: 12 | N1: 13
B2: Saturday | C2: Sunday | D2: Monday | E2: Tuesday | F2: Wednesday | G2: Thursday | H2: Friday | I2: Saturday | J2: Sunday | K2: Monday | L2: Tuesday | M2: Wednesday | N2: Thursday
B3: 46235 | C3: 46236 | D3: 46237 | E3: 46238 | F3: 46239 | G3: 46240 | H3: 46241 | I3: 46242 | J3: 46243 | K3: 46244 | L3: 46245 | M3: 46246 | N3: 46247
B4: SITE MANAGER ONSITE
B5: SITE MARK OUT | F5: EVENT OPS TEAM ONSITE
B6: 8:00am | F6: 7:00am
F11: FESTIVAL COMMENCES
F12: 3:30pm
F14: AC MILAN V INTER
F15: Gates: 5.30pm
F16: KO: 7.00pm

Sheet MASTER SCHEDULE
B1: CALCIO ITALIANO 2026 Little Italy Festival
B2: BUILD SCHEDULE
B3: Saturday 1st August 2026 - Tuesday 12th August 2026
A4: 46235
A5: START | B5: FINISH | C5: TYPE | D5: SUPPLIER | E5: ACTION | F5: LOCATION | G5: SITE POINT OF CONTACT | H5: NOTES | I5: COMPLETED
A6: 700 | B6: 2pm | C6: ON-SITE | D6: KYRON | E6: PM/ Site Manager Onsite (Markout stage/site infrastructure) | G6: PERSON 1 | I6: FALSE
A7: 7am | B7: 0.35416667 | C7: COLLECTION | D7: KYRON | E7: Pack Site Tool Chest at Warehouse > Deliver to Site | I7: FALSE
A8: 700 | B8: 1300 | C8: COLLECTION | D8: TBC | E8: Safety Officer Onsite | I8: FALSE
A9: 700 | B9: 1pm | C9: ON-SITE | D9: KYRON | E9: 2x Site Crew onsite | I9: FALSE
A10: 0.29166667 | B10: 0.35416667 | C10: ON-SITE | D10: PERTH HIRE SHOP | E10: 50x trakmatt | H10: ON-SITE | I10: FALSE | J10: Traffic control onsite (Camfield dr site entry) | M10: ON-SITE | N10: ESM | O10: Traffic control onsite (Camfield dr site entry) | R10: ON-SITE | S10: ESM | T10: Traffic control onsite (Camfield dr site entry) | W10: ON-SITE | X10: ESM | Y10: Traffic control onsite (Camfield dr site entry)
A11: 8am | B11: 10am | C11: DELIVERY | D11: EVENT FLOORING WA | E11: 40x Terratrak | I11: FALSE
A12: 8am | B12: 10am | C12: DELIVERY | D12: PERTH HIRE SHOP | E12: 10D Scissor, 3t AT Fork in compound | I12: FALSE
A13: 0.29166667 | B13: 10am | C13: DELIVERY | D13: KYRON | E13: Site Water Delivered | I13: FALSE
A14: 0.29166667 | B14: 1pm | C14: INSTALL | D14: FENCED / KYRON | E14: Build Ops Compound fenceline (Scrim) | Crane pl or lawn | I14: FALSE
A15: 9:00am | B15: 1pm | C15: DELIVERY | D15: KYRON | E15: Chocks / 20x 4ft trestles delivered | I15: FALSE
A16: 9:00am | B16: 1pm | C16: DELIVERY | D16: KYRON | E16: Set up site office / Ops compound | I16: FALSE
A17: 9:00am | B17: 1pm | C17: INSTALL | D17: PERTH HIRE SHOP | E17: Generators | 1x 60kva | I17: FALSE
A18: 1700 | B18: 700 | C18: SECURITY | D18: KYRON | E18: Secure Ops Compound | I18: FALSE
A19: =A4+1 -> 46236
A20: START | B20: FINISH | C20: TYPE | D20: SUPPLIER | E20: ACTION | F20: LOCATION | G20: SITE POINT OF CONTACT | H20: NOTES
A21: 0.29166667 | B21: 0.72916667 | C21: COLLECTION | D21: KYRON | I21: FALSE
A22: 1800 | B22: 700 | C22: COLLECTION | I22: FALSE
A23: =A19+1 -> 46237
A24: START | B24: FINISH | C24: TYPE | D24: SUPPLIER | E24: ACTION | F24: LOCATION | G24: SITE POINT OF CONTACT | H24: NOTES | J24: Traffic control onsite (Camfield dr site entry) | M24: ON-SITE | N24: ESM | O24: Traffic control onsite (Camfield dr site entry) | R24: ON-SITE | S24: ESM | T24: Traffic control onsite (Camfield dr site entry) | W24: ON-SITE | X24: ESM | Y24: Traffic control onsite (Camfield dr site entry)
A25: 0.29166667 | B25: 5pm | C25: ON-SITE | D25: KYRON | I25: FALSE
A26: 0.29166667 | B26: 0.72916667 | C26: ON-SITE | D26: KYRON | I26: FALSE
A27: 0.29166667 | B27: 0.72916667 | C27: ON-SITE | H27: ON-SITE | I27: FALSE
A28: 0.29166667 | B28: 0.72916667 | C28: ON-SITE | I28: FALSE
A29: 0.29166667 | B29: 0.72916667 | C29: INSTALL | I29: FALSE
A30: 700 | B30: 1730 | C30: ON-SITE | I30: FALSE
A31: 1800 | B31: 700 | C31: SECURITY | D31: VL | E31: Compound Secured overnight | I31: FALSE
A32: =A23+1 -> 46238
A33: START | B33: FINISH | C33: TYPE | D33: SUPPLIER | E33: ACTION | F33: LOCATION | G33: SITE POINT OF CONTACT | H33: NOTES
A34: 0.29166667 | C34: ON-SITE | D34: KYRON
J38: Traffic control onsite (Camfield dr site entry) | M38: ON-SITE | N38: ESM | O38: Traffic control onsite (Camfield dr site entry) | R38: ON-SITE | S38: ESM | T38: Traffic control onsite (Camfield dr site entry) | W38: ON-SITE | X38: ESM | Y38: Traffic control onsite (Camfield dr site entry)
A39: 1800 | B39: 700 | C39: SECURITY | D39: VL | E39: Compound Secured overnight
A40: =A32+1 -> 46239 | D40: EVENT DAY 1
A41: START | B41: FINISH | C41: TYPE | D41: SUPPLIER | E41: ACTION | F41: LOCATION | G41: SITE POINT OF CONTACT | H41: NOTES
A42: 0.29166667 | C42: ON-SITE | D42: KYRON | I42: FALSE
D43: KYRON | E43: 3x Site Crew onsite | I43: FALSE
A44: 0.29166667 | C44: INSTALL | I44: FALSE
A45: 0.29166667 | C45: ON-SITE | H45: ON-SITE | I45: FALSE
A46: 0.29166667 | C46: INSTALL | I46: FALSE
A47: 0.29166667 | C47: COLLECTION | I47: FALSE
C48: INSTALL | I48: FALSE
C49: DELIVERY | I49: FALSE
C50: DELIVERY | I50: FALSE
C51: INSTALL | I51: FALSE
C52: INSTALL | I52: FALSE
C53: INSTALL | I53: FALSE | J53: Traffic control onsite (Camfield dr site entry) | M53: ON-SITE | N53: ESM | O53: Traffic control onsite (Camfield dr site entry) | R53: ON-SITE | S53: ESM | T53: Traffic control onsite (Camfield dr site entry) | W53: ON-SITE | X53: ESM | Y53: Traffic control onsite (Camfield dr site entry)
C54: DELIVERY | I54: FALSE
C55: DELIVERY | I55: FALSE
C56: INSTALL | I56: FALSE
C57: DELIVERY | I57: FALSE
C58: INSTALL | I58: FALSE
A59: 1200 | B59: 1400 | C59: DELIVERY | I59: FALSE
C60: INSTALL | I60: FALSE
A61: 1800 | B61: 700 | C61: SECURITY | D61: VL | E61: Compound Secured overnight | I61: FALSE
A62: =A40+1 -> 46240 | D62: EVENT DAY 2
A63: START | B63: FINISH | C63: TYPE | D63: SUPPLIER | E63: ACTION | F63: LOCATION | G63: SITE POINT OF CONTACT | H63: NOTES
C64: ON-SITE | D64: KYRON | I64: FALSE
C65: ON-SITE | I65: FALSE
C66: ON-SITE | H66: ON-SITE | I66: FALSE
A67: 700 | B67: 1700 | C67: INSTALL | I67: FALSE
C68: INSTALL | I68: FALSE
C69: INSTALL | I69: FALSE
C70: DELIVERY | I70: FALSE
C71: INSTALL | I71: FALSE
C72: DELIVERY | I72: FALSE
C73: ON-SITE | I73: FALSE
C74: INSTALL | I74: FALSE | J74: Traffic control onsite (Camfield dr site entry) | M74: ON-SITE | N74: ESM | O74: Traffic control onsite (Camfield dr site entry) | R74: ON-SITE | S74: ESM | T74: Traffic control onsite (Camfield dr site entry) | W74: ON-SITE | X74: ESM | Y74: Traffic control onsite (Camfield dr site entry)
C75: DELIVERY | I75: FALSE
C76: ON-SITE | I76: FALSE
A77: 1800 | B77: 700 | C77: SECURITY | D77: ACE SECURITY | E77: Compound Secured overnight | I77: FALSE
A78: =A62+1 -> 46241 | D78: SHOWDAY
A79: START | B79: FINISH | C79: TYPE | D79: SUPPLIER | E79: ACTION | F79: LOCATION | G79: SITE POINT OF CONTACT | H79: NOTES
A80: 0.29166667 | C80: COLLECTION | D80: KYRON | I80: FALSE
A81: 0.29166667 | C81: ON-SITE | I81: FALSE
A82: 0.29166667 | C82: ON-SITE | H82: ON-SITE | I82: FALSE
A83: 0.375 | C83: ON-SITE | I83: FALSE
I84: FALSE
A85: 0.29166667 | C85: INSTALL | I85: FALSE
A86: 0.29166667 | C86: ON-SITE | I86: FALSE
A87: 0.54166667 | C87: ON-SITE | I87: FALSE
A88: 0.29166667 | C88: INSTALL | I88: FALSE
A89: 0.41666667 | C89: ON-SITE | I89: FALSE
C90: SHOW TIME | I90: FALSE | J90: Traffic control onsite (Camfield dr site entry) | M90: ON-SITE | N90: ESM | O90: Traffic control onsite (Camfield dr site entry) | R90: ON-SITE | S90: ESM | T90: Traffic control onsite (Camfield dr site entry) | W90: ON-SITE | X90: ESM | Y90: Traffic control onsite (Camfield dr site entry)
I91: FALSE
I92: FALSE
I93: FALSE
I94: FALSE
I95: FALSE
I96: FALSE
A97: 0.9375 | I97: FALSE
C98: BUMP OUT | I98: FALSE
C99: BUMP OUT | I99: FALSE
A100: 0.9375 | B100: 0.041666667 | C100: INSTALL | I100: FALSE
A101: 1800 | B101: 700 | C101: SECURITY | D101: Venueslive | E101: Asset secuirty overnight | I101: FALSE
A102: =A78+1 -> 46242
A103: START | B103: FINISH | C103: TYPE | D103: SUPPLIER | E103: ACTION | F103: LOCATION | G103: SITE POINT OF CONTACT | H103: NOTES
...

Sheet PRODUCTION SCHEDULE
A1: PRODUCTION SCHEDULE
A2: 44927 | C2: ACTIVITY | D2: NOTES
A3: START | B3: FINISH
A10: =A2+1 -> 44928 | C10: ACTIVITY | D10: NOTES
A11: START | B11: FINISH
A18: =A10+1 -> 44929 | C18: ACTIVITY | D18: NOTES
A19: START | B19: FINISH
A26: =A18+1 -> 44930 | C26: ACTIVITY | D26: NOTES
A27: START | B27: FINISH
A34: =A26+1 -> 44931 | C34: ACTIVITY | D34: NOTES
A35: START | B35: FINISH
A42: =A34+1 -> 44932 | C42: ACTIVITY | D42: NOTES
A43: START | B43: FINISH

Sheet TRANSPORT SCHEDULE
A1: TRANSPORT SCHEDULE
A2: IN-COMING
A3: DATE | B3: TIME | C3: ITEM | D3: FROM | E3: TRUCK TYPE | F3: DOORS FACING | G3: GATE ENTRY | H3: CONTACT PERSON
A4: 44963
A10: OUT-GOING
A11: DATE | B11: TIME | C11: ITEM | D11: FROM | E11: TRUCK TYPE | F11: DOORS FACING | G11: GATE ENTRY | H11: CONTACT PERSON

Sheet MAJOR STRUCTURES
A1: MAJOR STRUCTURES - CALSIO ITALIANO 2026
A2: MARQUEES | C2: MARQUEE NAME | D2: SIZE | F2: PEGGED | G2: WEIGHTED | H2: LIGHTING | I2: WALLS | J2: NOTES | K2: DOCS RECIEVED | L2: LINK | M2: ENGINEER SIGN-OFF
A3: RESPONSIBLE | B3: TYPE | D3: LENGTH | E3: WIDTH
A4: KYRON | B4: ROBIAN | C4: VENDORS | D4: 3m | E4: 3m | F4: FALSE | G4: TRUE | H4: TRUE | I4: ALL WALLS | J4: 6x Green, 6x Red, 6x White | K4: FALSE | M4: FALSE
A5: KYRON | B5: HOKKER | C5: PASTA | D5: 5m | E5: 5m | F5: FALSE | G5: TRUE | H5: TRUE | I5: ALL WALLS | K5: FALSE | M5: FALSE
A6: KYRON | B6: HOKKER | C6: MERCH (BRIDGE) | D6: 12m | E6: 3m | F6: FALSE | G6: TRUE | H6: TRUE | I6: ALL WALLS | K6: FALSE | M6: FALSE
F7: FALSE | G7: FALSE | H7: FALSE | K7: FALSE | M7: FALSE
F8: FALSE | G8: FALSE | H8: FALSE | K8: FALSE | M8: FALSE
F9: FALSE | G9: FALSE | H9: FALSE | K9: FALSE | M9: FALSE
A10: OTHER | C10: STRUCTURE NAME | D10: SIZE | F10: PEGGED | G10: WEIGHTED | H10: NOTES | K10: DOCS RECIEVED | L10: LINK | M10: ENGINEER SIGN-OFF
A11: RESPONSIBLE | B11: TYPE | D11: LENGTH | E11: WIDTH
F12: FALSE | G12: FALSE | K12: FALSE | M12: FALSE
F13: FALSE | G13: FALSE | K13: FALSE | M13: FALSE
F14: FALSE | G14: FALSE | K14: FALSE | M14: FALSE
F15: FALSE | G15: FALSE | K15: FALSE | M15: FALSE
F16: FALSE | G16: FALSE | K16: FALSE | M16: FALSE
F17: FALSE | G17: FALSE | K17: FALSE | M17: FALSE

Sheet FENCING
A1: FENCING
A2: 1.8M TEMPORARY FENCING
A3: LOCATION | B3: TYPE | C3: LENGTH (M) | D3: MITIGATION | E3: TOTAL | F3: NOTES
A4: OPS COMPOUND | B4: INSTALL | C4: 55 | D4: =C4*0.1 -> 5.5 | E4: =SUM(C4:D4) -> 60.5
A5: STAGE BOH | B5: INSTALL | C5: 70 | D5: =C5*0.1 -> 7 | E5: =SUM(C5:D5) -> 77
A6: BAR BOH | B6: INSTALL | C6: 70 | D6: =C6*0.1 -> 7 | E6: =SUM(C6:D6) -> 77
A7: SOUTH OVAL / CAMFIELD | B7: INSTALL | C7: 30 | D7: =C7*0.1 -> 3 | E7: =SUM(C7:D7) -> 33
A9: DOUBLE GATES / WHEELS | B9: INSTALL | C9: 3 | D9: =C9*0.1 -> 0.3 | E9: =SUM(C9:D9) -> 3.3
D10: =C10*0.1 -> 0 | E10: =SUM(C10:D10) -> 0 | F10: =SUM(E4:E9) -> 250.8
A11: CCB (CROWD CONTROL BARRIER)
A12: LOCATION | B12: TYPE | C12: LENGTH | D12: MITIGATION | E12: TOTAL | F12: NOTES
A13: 150 | D13: =C13*0.1 -> 0 | E13: =SUM(C13:D13) -> 0
D14: =C14*0.1 -> 0 | E14: =SUM(C14:D14) -> 0
D15: =C15*0.1 -> 0 | E15: =SUM(C15:D15) -> 0
D16: =C16*0.1 -> 0 | E16: =SUM(C16:D16) -> 0
D17: =C17*0.1 -> 0 | E17: =SUM(C17:D17) -> 0
D18: =C18*0.1 -> 0 | E18: =SUM(C18:D18) -> 0
A19: PUNTER BARRIER
A20: LOCATION | B20: TYPE | C20: LENGTH | D20: MITIGATION | E20: TOTAL | F20: NOTES
D21: =C21*0.1 -> 0 | E21: =SUM(C21:D21) -> 0
D22: =C22*0.1 -> 0 | E22: =SUM(C22:D22) -> 0
D23: =C23*0.1 -> 0 | E23: =SUM(C23:D23) -> 0
D24: =C24*0.1 -> 0 | E24: =SUM(C24:D24) -> 0
D25: =C25*0.1 -> 0 | E25: =SUM(C25:D25) -> 0
D26: =C26*0.1 -> 0 | E26: =SUM(C26:D26) -> 0
A27: WHITE PICKET
A28: LOCATION | B28: TYPE | C28: LENGTH | D28: MITIGATION | E28: TOTAL | F28: NOTES
D29: =C29*0.1 -> 0 | E29: =SUM(C29:D29) -> 0
D30: =C30*0.1 -> 0 | E30: =SUM(C30:D30) -> 0
D31: =C31*0.1 -> 0 | E31: =SUM(C31:D31) -> 0
D32: =C32*0.1 -> 0 | E32: =SUM(C32:D32) -> 0
D33: =C33*0.1 -> 0 | E33: =SUM(C33:D33) -> 0
D34: =C34*0.1 -> 0 | E34: =SUM(C34:D34) -> 0

Sheet FURNITURE DISTRO
A1: FURNITURE DISTRO
A2: LOCATION | B2: CHAIRS | C2: TABLES | E2: COUCH | F2: FRIDGE | G2: ICE TUB | H2: FANS | I2: BUBBLER | J2: LINEN | K2: COAT RACK | L2: MIRROR
C3: 1.8M | D3: 2.4M
A10: SPARE
A11: TOTAL | B11: =SUM(B4:B10) -> 0 | C11: =SUM(C4:C10) -> 0 | D11: =SUM(D4:D10) -> 0 | E11: =SUM(E4:E10) -> 0 | F11: =SUM(F4:F10) -> 0 | G11: =SUM(G4:G10) -> 0 | H11: =SUM(H4:H10) -> 0 | I11: =SUM(I4:I10) -> 0 | ... L11: =SUM(L4:L10) -> 0
A12: SUPPLIER

Sheet TOILET RATIO CALC
A1: TOILET RATIO CALCULATOR
A2: GENERAL AREA | D2: VIP AREA | Z2: SET RATIO
A3: TYPE | B3: QUANTITY | C3: PANS | D3: TYPE | E3: QUANTITY | F3: PANS | Z3: RATIO
A4: 16 PAN BLOCK | B4: 0 | C4: =B4*16 -> 0 | D4: 16 PAN BLOCK | E4: 0 | F4: =E4*16 -> 0
A5: URINAL BLOCK | B5: 0 | C5: =16*B5 -> 0 | D5: URINAL BLOCK | E5: 0 | F5: =16*E5 -> 0
A6: SINGLE CHEM | B6: 40 | C6: =1*B6 -> 40 | D6: SINGLE CHEM | E6: 0 | F6: =1*E6 -> 0
A7: ACROD | B7: 2 | C7: =1*B7 -> 2 | D7: ACROD | E7: 0 | F7: =1*E7 -> 0
A8: TOTAL PANS | C8: =SUM(C4:C7) -> 42 | D8: TOTAL PANS | F8: =SUM(F4:F7) -> 0
A9: CAPACITY | C9: 3000 | D9: CAPACITY | F9: 0
A10: 75 | B10: TOILET RATIO | C10: =C9/C8 -> 71.428571 | D10: 45 | E10: TOILET RATIO | F10: =F9/F8 -> #DIV/0!

Sheet SITE MAP
A1: SITE MAP
A2: VERSION | B2: LINK

Sheet Criteria
A1: KYLE BAILEY (KB)
A2: FRED (PHS)
A3: FRANK M (FM)
A4: WENDY (VL)
A5: TYLER (TWA)
A6: MIZZICA
A9: ON-SITE
A10: INSTALL
A11: COLLECTION
A12: DELIVERY
A13: SHOW TIME
A14: ON-SITE
... A52: INSTALL
